{
	"configurations" : 
	[
		{
			"directories" : 
			[
				{
					"build" : ".",
					"jsonFile" : "directory-.-Debug-d0094a50bb2071803777.json",
					"minimumCMakeVersion" : 
					{
						"string" : "3.23"
					},
					"projectIndex" : 0,
					"source" : ".",
					"targetIndexes" : 
					[
						0
					]
				}
			],
			"name" : "Debug",
			"projects" : 
			[
				{
					"directoryIndexes" : 
					[
						0
					],
					"name" : "stats",
					"targetIndexes" : 
					[
						0
					]
				}
			],
			"targets" : 
			[
				{
					"directoryIndex" : 0,
					"id" : "stats::@6890427a1f51a3e7e1df",
					"jsonFile" : "target-stats-Debug-453107be8e10e9a2d16e.json",
					"name" : "stats",
					"projectIndex" : 0
				}
			]
		}
	],
	"kind" : "codemodel",
	"paths" : 
	{
		"build" : "D:/2023 S1/COMP90024_Cluster_and_Cloud_Computing/Assignment_1/stats/cmake-build-debug",
		"source" : "D:/2023 S1/COMP90024_Cluster_and_Cloud_Computing/Assignment_1/stats"
	},
	"version" : 
	{
		"major" : 2,
		"minor" : 4
	}
}
